source_azure_table/__init__.py
source_azure_table/azure_table.py
source_azure_table/constants.py
source_azure_table/run.py
source_azure_table/source.py
source_azure_table/spec.json
source_azure_table/streams.py
airbyte_source_azure_table-0.1.57.dist-info/METADATA
airbyte_source_azure_table-0.1.57.dist-info/WHEEL
airbyte_source_azure_table-0.1.57.dist-info/entry_points.txt
airbyte_source_azure_table-0.1.57.dist-info/RECORD
