Metadata-Version: 2.1
Name: airbyte-source-azure-table
Version: 0.1.57
Summary: Source implementation for Azure Table.
Home-page: https://airbyte.com
License: ELv2
Author: Airbyte
Author-email: contact@airbyte.io
Requires-Python: >=3.9,<3.12
Classifier: License :: Other/Proprietary License
Classifier: Programming Language :: Python :: 3
Classifier: Programming Language :: Python :: 3.9
Classifier: Programming Language :: Python :: 3.10
Classifier: Programming Language :: Python :: 3.11
Requires-Dist: airbyte-cdk (==0.80.0)
Requires-Dist: azure.data.tables (>=12.5.0,<13.0.0)
Project-URL: Documentation, https://docs.airbyte.com/integrations/sources/azure-table
Project-URL: Repository, https://github.com/airbytehq/airbyte
